fastapi_guard-4.2.1.dist-info/licenses/LICENSE
guard/__init__.py
guard/middleware.py
guard/models.py
guard/py.typed
guard/utils.py
guard/core/__init__.py
guard/core/py.typed
guard/core/behavioral/__init__.py
guard/core/behavioral/context.py
guard/core/behavioral/processor.py
guard/core/behavioral/py.typed
guard/core/bypass/__init__.py
guard/core/bypass/context.py
guard/core/bypass/handler.py
guard/core/bypass/py.typed
guard/core/checks/__init__.py
guard/core/checks/base.py
guard/core/checks/helpers.py
guard/core/checks/pipeline.py
guard/core/checks/py.typed
guard/core/checks/implementations/__init__.py
guard/core/checks/implementations/authentication.py
guard/core/checks/implementations/cloud_ip_refresh.py
guard/core/checks/implementations/cloud_provider.py
guard/core/checks/implementations/custom_request.py
guard/core/checks/implementations/custom_validators.py
guard/core/checks/implementations/emergency_mode.py
guard/core/checks/implementations/https_enforcement.py
guard/core/checks/implementations/ip_security.py
guard/core/checks/implementations/py.typed
guard/core/checks/implementations/rate_limit.py
guard/core/checks/implementations/referrer.py
guard/core/checks/implementations/request_logging.py
guard/core/checks/implementations/request_size_content.py
guard/core/checks/implementations/required_headers.py
guard/core/checks/implementations/route_config.py
guard/core/checks/implementations/suspicious_activity.py
guard/core/checks/implementations/time_window.py
guard/core/checks/implementations/user_agent.py
guard/core/events/__init__.py
guard/core/events/metrics.py
guard/core/events/middleware_events.py
guard/core/events/py.typed
guard/core/initialization/__init__.py
guard/core/initialization/handler_initializer.py
guard/core/initialization/py.typed
guard/core/responses/__init__.py
guard/core/responses/context.py
guard/core/responses/factory.py
guard/core/responses/py.typed
guard/core/routing/__init__.py
guard/core/routing/context.py
guard/core/routing/py.typed
guard/core/routing/resolver.py
fastapi_guard-4.2.1.dist-info/METADATA
fastapi_guard-4.2.1.dist-info/WHEEL
fastapi_guard-4.2.1.dist-info/top_level.txt
fastapi_guard-4.2.1.dist-info/RECORD
