Metadata-Version: 2.4
Name: fastapi_guard
Version: 4.2.1
Summary: A security library for FastAPI to control IPs, log requests, and detect penetration attempts.
Author-email: Renzo Franceschini <rennf93@users.noreply.github.com>
License: MIT
Project-URL: Homepage, https://github.com/rennf93/fastapi-guard
Classifier: Development Status :: 5 - Production/Stable
Classifier: Framework :: FastAPI
Classifier: Intended Audience :: Developers
Classifier: License :: OSI Approved :: MIT License
Classifier: Operating System :: OS Independent
Classifier: Programming Language :: Python :: 3
Classifier: Programming Language :: Python :: 3.10
Classifier: Programming Language :: Python :: 3.11
Classifier: Programming Language :: Python :: 3.12
Classifier: Programming Language :: Python :: 3.13
Requires-Python: <3.14,>=3.10
License-File: LICENSE
Requires-Dist: cachetools
Requires-Dist: fastapi
Requires-Dist: httpx
Requires-Dist: maxminddb
Requires-Dist: pydantic
Requires-Dist: redis
Requires-Dist: requests
Requires-Dist: starlette
Requires-Dist: typing-extensions
Requires-Dist: uvicorn
Provides-Extra: dev
Requires-Dist: aiohttp; extra == "dev"
Requires-Dist: bandit[toml]; extra == "dev"
Requires-Dist: deptry; extra == "dev"
Requires-Dist: fastapi-guard-agent; extra == "dev"
Requires-Dist: httpx; extra == "dev"
Requires-Dist: matplotlib; extra == "dev"
Requires-Dist: mkdocs; extra == "dev"
Requires-Dist: mkdocstrings; extra == "dev"
Requires-Dist: mkdocstrings-python; extra == "dev"
Requires-Dist: mkdocs-material; extra == "dev"
Requires-Dist: mypy; extra == "dev"
Requires-Dist: numpy; extra == "dev"
Requires-Dist: pip-audit; extra == "dev"
Requires-Dist: pre-commit; extra == "dev"
Requires-Dist: pymarkdownlnt; extra == "dev"
Requires-Dist: pytest; extra == "dev"
Requires-Dist: pytest-asyncio; extra == "dev"
Requires-Dist: pytest-cov; extra == "dev"
Requires-Dist: pytest-mock; extra == "dev"
Requires-Dist: radon; extra == "dev"
Requires-Dist: ruff; extra == "dev"
Requires-Dist: safety; extra == "dev"
Requires-Dist: semgrep; extra == "dev"
Requires-Dist: types-cachetools; extra == "dev"
Requires-Dist: types-requests; extra == "dev"
Requires-Dist: vulture; extra == "dev"
Requires-Dist: xenon; extra == "dev"
Dynamic: license-file
